amojowrapper/__init__.py
amojowrapper/__main__.py
amojowrapper/actions/__init__.py
amojowrapper/actions/channel/__init__.py
amojowrapper/actions/channel/action.py
amojowrapper/actions/channel/schemes.py
amojowrapper/actions/chat/__init__.py
amojowrapper/actions/chat/action.py
amojowrapper/actions/chat/schemes.py
amojowrapper/actions/delivery/__init__.py
amojowrapper/actions/delivery/action.py
amojowrapper/actions/delivery/schemes.py
amojowrapper/actions/history/__init__.py
amojowrapper/actions/history/action.py
amojowrapper/actions/history/schemes.py
amojowrapper/actions/message/__init__.py
amojowrapper/actions/message/action.py
amojowrapper/actions/message/schemes.py
amojowrapper/actions/react/__init__.py
amojowrapper/actions/react/action.py
amojowrapper/actions/react/schemes.py
amojowrapper/actions/typing/__init__.py
amojowrapper/actions/typing/action.py
amojowrapper/actions/typing/schemes.py
amojowrapper/client.py
amojowrapper/core/__init__.py
amojowrapper/core/client.py
amojowrapper/helpers/__init__.py
amojowrapper/helpers/endpoint.py
amojowrapper/helpers/headers.py
amojowrapper/request/__init__.py
amojowrapper/request/_request.py
amojowrapper/request/exceptions.py
amojowrapper/request/request.py
amojowrapper/validators/__init__.py
amojowrapper/validators/webhook.py
amojowrapper-0.1.1.dist-info/LICENSE
amojowrapper-0.1.1.dist-info/METADATA
amojowrapper-0.1.1.dist-info/WHEEL
amojowrapper-0.1.1.dist-info/entry_points.txt
amojowrapper-0.1.1.dist-info/RECORD
